aiogram_magick/__init__.py
aiogram_magick/sqlite.py
aiogram_magick-0.1.0.dist-info/LICENSE
aiogram_magick-0.1.0.dist-info/METADATA
aiogram_magick-0.1.0.dist-info/WHEEL
aiogram_magick-0.1.0.dist-info/RECORD
