Metadata-Version: 2.1
Name: aiogram_magick
Version: 0.1.0
Summary: Magick for Aiogram 3.x-based Telegram bots
Home-page: https://github.com/arichr/aiogram-magick
License: MIT
Keywords: aiogram,storage,sqlite,compontents,component,telegram,bot,async,asynchronous,api,messaging
Author: Arisu Wonderland
Author-email: arisuchr@riseup.net
Requires-Python: >=3.8,<4.0
Classifier: Development Status :: 4 - Beta
Classifier: Environment :: Plugins
Classifier: Intended Audience :: Developers
Classifier: License :: OSI Approved
Classifier: License :: OSI Approved :: MIT License
Classifier: Operating System :: OS Independent
Classifier: Programming Language :: Python
Classifier: Programming Language :: Python :: 3
Classifier: Programming Language :: Python :: 3.8
Classifier: Programming Language :: Python :: 3.9
Classifier: Programming Language :: Python :: 3.10
Classifier: Programming Language :: Python :: 3.11
Classifier: Programming Language :: Python :: 3.12
Classifier: Programming Language :: Python :: 3 :: Only
Classifier: Programming Language :: Python :: 3.13
Classifier: Programming Language :: Python :: 3.14
Classifier: Topic :: Database
Classifier: Topic :: Software Development :: Libraries
Classifier: Topic :: Software Development :: Libraries :: Python Modules
Requires-Dist: aiogram (>=3.10.0,<4.0.0)
Project-URL: Documentation, https://arichr.github.io/aiogram-magick/
Project-URL: Repository, https://github.com/arichr/aiogram-magick
